askyai/__init__.py
askyai-0.1.0.dist-info/licenses/LICENSE
askyai-0.1.0.dist-info/METADATA
askyai-0.1.0.dist-info/WHEEL
askyai-0.1.0.dist-info/top_level.txt
askyai-0.1.0.dist-info/RECORD
